_yappi.cp312-win32.pyd
yappi.py
yappi-1.7.3.dist-info/licenses/LICENSE
yappi-1.7.3.dist-info/METADATA
yappi-1.7.3.dist-info/WHEEL
yappi-1.7.3.dist-info/entry_points.txt
yappi-1.7.3.dist-info/top_level.txt
yappi-1.7.3.dist-info/RECORD
